Components/register.v
module register #(parameter WIDHT=8)(input i_clk, i_rst_n,
		input [WIDHT-1:0] i_D,
		output reg [WIDHT-1:0] o_Q);


always @(posedge i_clk, negedge i_rst_n)
begin
	if (!i_rst_n)
		o_Q <= 0;
	else begin
		o_Q <= i_D;
	end

end

endmodule

display/Components/mux4in1.v
module mux4in1 #(parameter WIDHT=8) (input wire [3:0] i_en,
		input wire [WIDHT-1:0] i_D0,
		input wire [WIDHT-1:0] i_D1,
		input wire [WIDHT-1:0] i_D2,
		input wire [WIDHT-1:0] i_D3,
		output reg [WIDHT-1:0] o_Q);



always @(*)
begin

	case(1) 
		i_en[0]: o_Q <= i_D0;
		i_en[1]: o_Q <= i_D1;
		i_en[2]: o_Q <= i_D2;
		i_en[3]: o_Q <= i_D3;
	endcase

end


endmodule

display/Components/decoder.v

module decoder #(parameter WIDTH=4)(input [WIDTH>>2:0] i_A,
		output [WIDTH-1:0] o_P);


assign o_P = 1 << i_A;

/*
always @(*)
begin
	o_P = 1 << i_A;
end
*/
endmodule

display.v
//
//
//	SIZE multiple 4
//
//	interfase --> reg --> combination logic --> reg --> output
//


module display #(parameter SIZE=4) (input i_clk, i_rst_n,
		input [10:0] i_comm,
		input [(SIZE<<3)-1:0] i_data,
//		input [7:0] i_data0,
//		input [7:0] i_data1,
//		input [7:0] i_data2,
//		input [7:0] i_data3,
		output [7:0] o_data,
		output o_E, o_RS, o_RW);


genvar i;


wire [7:0] byte [0:SIZE-1];
reg [SIZE-1:0] en;

wire	[10:0]	command;
wire	[7:0]	data [0:SIZE-1];
wire	[7:0]	o_mux [0:(SIZE>>2)];
wire	[7:0]	mux;


wire	[SIZE-1:0] o_decoder;

//assign byte[0] = i_data0;
//assign byte[1] = i_data1;
//assign byte[2] = i_data2;
//assign byte[3] = i_data3;

//control ();



//
// decode i_data
//

///*
generate
	for(i = 0; i < SIZE; i = i+1)
	begin
		assign byte[i] = i_data[i*8+7:i*8];
	end
endgenerate
//*/



//
// create register
//

register #(11) m_reg_comm(.i_clk(i_clk),
		.i_rst_n(i_rst_n),
		.i_D(i_comm),
		.o_Q(command));

generate
	for(i = 0; i < SIZE; i = i+1)
	begin
		register m_reg_data(.i_clk(i_clk),
				.i_rst_n(i_rst_n),
				.i_D(byte[i]),
				.o_Q(data[i]));
	end
endgenerate


//
// combinating logic
//



decoder #(.WIDTH(SIZE)) m_decoder(.i_A(command[SIZE>>2:0]),
		.o_P(o_decoder));


/*
*
* formation of en
*
*/
integer j;
always @(*)
begin
	en[0] = ~command[10];
	for(j = 1; j < SIZE; j = j+1)
	begin
		en[j] = command[10] && o_decoder[j-1];
	end
end



//
// create multiplaxer
//

mux4in1 mux0 (.i_en(en),
		.i_D0(command[7:0]),
		.i_D1(data[1]),
		.i_D2(data[2]),
		.i_D3(data[3]),
		.o_Q(o_mux[0]));

generate
	assign mux = o_mux[0];
	for(i=1; i < (SIZE >> 2); i = i+1)
	begin
		mux4in1 m_mux (.i_en(en),
				.i_D0(data[0+i*4]),
				.i_D1(data[1+i*4]),
				.i_D2(data[2+i*4]),
				.i_D3(data[3+i*4]),
				.o_Q(o_mux[i]));

		assign mux = mux || o_mux[i];
	end
endgenerate




//
// formation of the output signal
//

register m_reg_o_data(.i_clk(i_clk),
		.i_rst_n(i_rst_n),
		.i_D(mux),
		.o_Q(o_data));

register #(1) m_reg_o_rs(.i_clk(i_clk),
		.i_rst_n(i_rst_n),
		.i_D(command[8]),
		.o_Q(o_RS));

register #(1) m_reg_o_rw(.i_clk(i_clk),
		.i_rst_n(i_rst_n),
		.i_D(command[9]),
		.o_Q(o_RW));

assign o_E = i_clk;

endmodule

display/tb_display.v
`timescale 1 ns / 10 ps

module tb_display;

parameter SIZE=4;

reg clk, rst_n;
reg [10:0] ram;

reg [7:0] data [0:SIZE-1];
reg [(SIZE<<3)-1:0] data_all;


integer i;
always @(*)
begin
	data_all = {data[3], data[2], data[1], data[0]};
	for(i = 0; i < SIZE; i = i+1)
	begin
		//data_all[(8*i)+7:8*i] = data[i];
	end
end

display #(.SIZE(SIZE)) m_display(.i_clk(clk),
		.i_rst_n(rst_n),
		.i_comm(ram),
		.i_data(data_all));



initial
begin
	ram = 11'h7f0;
	data[0] = 8'hff;
	data[1] = 8'h0f;
	#60
	ram = 11'h302;
	data[0] = 8'h00;
	data[1] = 8'hf0;
end


initial
begin
	#0 rst_n = 0;
	#1 rst_n = 1;
end


initial 
begin
	clk = 0;
	forever #20 clk = ~clk;
end

initial 
begin
	$dumpfile("Debug/display.vcd");
	$dumpvars;
	#1000 $finish;
end


endmodule

Debug/display.vcd
$date
	Sat Sep 18 15:00:14 2021
$end
$version
	Icarus Verilog
$end
$timescale
	10ps
$end
$scope module tb_display $end
$var reg 1 ! clk $end
$var reg 32 " data_all [31:0] $end
$var reg 11 # ram [10:0] $end
$var reg 1 $ rst_n $end
$var integer 32 % i [31:0] $end
$scope module m_display $end
$var wire 1 ! i_clk $end
$var wire 11 & i_comm [10:0] $end
$var wire 32 ' i_data [31:0] $end
$var wire 1 $ i_rst_n $end
$var wire 8 ( mux [7:0] $end
$var wire 1 ) o_E $end
$var wire 4 * o_decoder [3:0] $end
$var wire 8 + o_data [7:0] $end
$var wire 1 , o_RW $end
$var wire 1 - o_RS $end
$var wire 11 . command [10:0] $end
$var reg 4 / en [3:0] $end
$var integer 32 0 j [31:0] $end
$scope begin genblk1[0] $end
$upscope $end
$scope begin genblk1[1] $end
$upscope $end
$scope begin genblk1[2] $end
$upscope $end
$scope begin genblk1[3] $end
$upscope $end
$scope begin genblk2[0] $end
$scope module m_reg_data $end
$var wire 8 1 i_D [7:0] $end
$var wire 1 ! i_clk $end
$var wire 1 $ i_rst_n $end
$var reg 8 2 o_Q [7:0] $end
$upscope $end
$upscope $end
$scope begin genblk2[1] $end
$scope module m_reg_data $end
$var wire 8 3 i_D [7:0] $end
$var wire 1 ! i_clk $end
$var wire 1 $ i_rst_n $end
$var reg 8 4 o_Q [7:0] $end
$upscope $end
$upscope $end
$scope begin genblk2[2] $end
$scope module m_reg_data $end
$var wire 8 5 i_D [7:0] $end
$var wire 1 ! i_clk $end
$var wire 1 $ i_rst_n $end
$var reg 8 6 o_Q [7:0] $end
$upscope $end
$upscope $end
$scope begin genblk2[3] $end
$scope module m_reg_data $end
$var wire 8 7 i_D [7:0] $end
$var wire 1 ! i_clk $end
$var wire 1 $ i_rst_n $end
$var reg 8 8 o_Q [7:0] $end
$upscope $end
$upscope $end
$scope module m_decoder $end
$var wire 2 9 i_A [1:0] $end
$var wire 4 : o_P [3:0] $end
$upscope $end
$scope module m_reg_comm $end
$var wire 11 ; i_D [10:0] $end
$var wire 1 ! i_clk $end
$var wire 1 $ i_rst_n $end
$var reg 11 < o_Q [10:0] $end
$upscope $end
$scope module m_reg_o_data $end
$var wire 8 = i_D [7:0] $end
$var wire 1 ! i_clk $end
$var wire 1 $ i_rst_n $end
$var reg 8 > o_Q [7:0] $end
$upscope $end
$scope module m_reg_o_rs $end
$var wire 1 ? i_D $end
$var wire 1 ! i_clk $end
$var wire 1 $ i_rst_n $end
$var reg 1 - o_Q $end
$upscope $end
$scope module m_reg_o_rw $end
$var wire 1 @ i_D $end
$var wire 1 ! i_clk $end
$var wire 1 $ i_rst_n $end
$var reg 1 , o_Q $end
$upscope $end
$scope module mux0 $end
$var wire 8 A i_D0 [7:0] $end
$var wire 8 B i_D1 [7:0] $end
$var wire 8 C i_D2 [7:0] $end
$var wire 8 D i_D3 [7:0] $end
$var wire 4 E i_en [3:0] $end
$var reg 8 F o_Q [7:0] $end
$upscope $end
$upscope $end
$upscope $end
$enddefinitions $end
#0
$dumpvars
b0 F
b1 E
b0 D
b0 C
b0 B
b0 A
0@
0?
b0 >
b0 =
b0 <
b11111110000 ;
b1 :
b0 9
b0 8
bx 7
b0 6
bx 5
b0 4
b1111 3
b0 2
b11111111 1
b100 0
b1 /
b0 .
0-
0,
b0 +
b1 *
0)
b0 (
bx0000111111111111 '
b11111110000 &
b100 %
0$
b11111110000 #
bx0000111111111111 "
0!
$end
#100
1$
#2000
b1111 (
b1111 =
b1111 F
1@
1?
b11110000 A
b100 0
b10 /
b10 E
b11111110000 .
b11111110000 <
bx 8
bx D
bx 6
bx C
b1111 4
b1111 B
b11111111 2
1)
1!
#4000
0)
0!
#6000
b10 (
b10 =
b10 F
b10 A
b100 *
b100 :
b10 9
b100 0
b1 /
b1 E
b1100000010 .
b1100000010 <
b1111 +
b1111 >
1-
1,
b0 1
b11110000 3
b100 %
bx1111000000000000 "
bx1111000000000000 '
1)
1!
b1100000010 #
b1100000010 &
b1100000010 ;
#8000
0)
0!
#10000
b10 +
b10 >
b11110000 4
b11110000 B
b0 2
1)
1!
#12000
0)
0!
#14000
1)
1!
#16000
0)
0!
#18000
1)
1!
#20000
0)
0!
#22000
1)
1!
#24000
0)
0!
#26000
1)
1!
#28000
0)
0!
#30000
1)
1!
#32000
0)
0!
#34000
1)
1!
#36000
0)
0!
#38000
1)
1!
#40000
0)
0!
#42000
1)
1!
#44000
0)
0!
#46000
1)
1!
#48000
0)
0!
#50000
1)
1!
#52000
0)
0!
#54000
1)
1!
#56000
0)
0!
#58000
1)
1!
#60000
0)
0!
#62000
1)
1!
#64000
0)
0!
#66000
1)
1!
#68000
0)
0!
#70000
1)
1!
#72000
0)
0!
#74000
1)
1!
#76000
0)
0!
#78000
1)
1!
#80000
0)
0!
#82000
1)
1!
#84000
0)
0!
#86000
1)
1!
#88000
0)
0!
#90000
1)
1!
#92000
0)
0!
#94000
1)
1!
#96000
0)
0!
#98000
1)
1!
#100000
0)
0!
